otf_api/__init__.py
otf_api/cache.py
otf_api/exceptions.py
otf_api/py.typed
otf_api/api/__init__.py
otf_api/api/_compat.py
otf_api/api/api.py
otf_api/api/client.py
otf_api/api/utils.py
otf_api/api/bookings/__init__.py
otf_api/api/bookings/booking_api.py
otf_api/api/bookings/booking_client.py
otf_api/api/members/__init__.py
otf_api/api/members/member_api.py
otf_api/api/members/member_client.py
otf_api/api/studios/__init__.py
otf_api/api/studios/studio_api.py
otf_api/api/studios/studio_client.py
otf_api/api/workouts/__init__.py
otf_api/api/workouts/workout_api.py
otf_api/api/workouts/workout_client.py
otf_api/auth/__init__.py
otf_api/auth/auth.py
otf_api/auth/user.py
otf_api/auth/utils.py
otf_api/models/__init__.py
otf_api/models/base.py
otf_api/models/mixins.py
otf_api/models/bookings/__init__.py
otf_api/models/bookings/bookings.py
otf_api/models/bookings/bookings_v2.py
otf_api/models/bookings/classes.py
otf_api/models/bookings/enums.py
otf_api/models/bookings/filters.py
otf_api/models/bookings/ratings.py
otf_api/models/members/__init__.py
otf_api/models/members/member_detail.py
otf_api/models/members/member_membership.py
otf_api/models/members/member_purchases.py
otf_api/models/members/notifications.py
otf_api/models/studios/__init__.py
otf_api/models/studios/enums.py
otf_api/models/studios/studio_detail.py
otf_api/models/studios/studio_services.py
otf_api/models/workouts/__init__.py
otf_api/models/workouts/body_composition_list.py
otf_api/models/workouts/challenge_tracker_content.py
otf_api/models/workouts/challenge_tracker_detail.py
otf_api/models/workouts/enums.py
otf_api/models/workouts/lifetime_stats.py
otf_api/models/workouts/out_of_studio_workout_history.py
otf_api/models/workouts/performance_summary.py
otf_api/models/workouts/telemetry.py
otf_api/models/workouts/workout.py
otf_api-0.15.4.dist-info/licenses/LICENSE
otf_api-0.15.4.dist-info/METADATA
otf_api-0.15.4.dist-info/WHEEL
otf_api-0.15.4.dist-info/top_level.txt
otf_api-0.15.4.dist-info/RECORD
