Metadata-Version: 2.4
Name: otf-api
Version: 0.15.4
Summary: Python OrangeTheory Fitness API Client
Author-email: Jessica Smith <j.smith.git1@gmail.com>
License-Expression: MIT
Project-URL: Documentation, https://otf-api.readthedocs.io/en/stable/
Classifier: Development Status :: 4 - Beta
Classifier: Intended Audience :: Developers
Classifier: Programming Language :: Python :: 3.11
Classifier: Topic :: Software Development :: Libraries :: Python Modules
Classifier: Topic :: Software Development :: Libraries
Classifier: Topic :: Internet :: WWW/HTTP
Classifier: Operating System :: OS Independent
Requires-Python: >=3.11
License-File: LICENSE
Requires-Dist: attrs<25,>=24.3.0
Requires-Dist: httpx>=0.27.2
Requires-Dist: humanize<5,>=4.9.0
Requires-Dist: inflection==0.5.*
Requires-Dist: pint==0.24.*
Requires-Dist: pycognito==2024.5.1
Requires-Dist: pydantic>=2.7.3
Requires-Dist: yarl<2,>=1.18.3
Requires-Dist: tenacity<10,>=9.0.0
Requires-Dist: cachetools>=5.5.0
Requires-Dist: pendulum>=3.1.0
Requires-Dist: diskcache>=5.6.3
Requires-Dist: platformdirs>=4.3.6
Requires-Dist: packaging>=24.2
Requires-Dist: coloredlogs>=15.0.1
Dynamic: license-file
